{
  "uttid": "0669-0002",
  "words": {
    "sentence": [
      "RECENTLY",
      "I",
      "HEARD",
      "SHE",
      "IS",
      "BEING",
      "CYBER",
      "BULLYING"
    ],
    "interval": [
      [
        0.0,
        0.71
      ],
      [
        0.77,
        0.93
      ],
      [
        0.93,
        1.34
      ],
      [
        1.34,
        1.64
      ],
      [
        1.64,
        1.84
      ],
      [
        1.84,
        2.16
      ],
      [
        2.16,
        2.69
      ],
      [
        2.69,
        3.01
      ]
    ],
    "disfluency_label": [
      0,
      0,
      1,
      0,
      0,
      0,
      0,
      0
    ],
    "att_based_D_on_src": {
      "interval": [
        [
          2.69,
          3.01
        ]
      ],
      "disfluency_label": [
        0,
        0,
        0,
        0,
        0,
        0,
        0,
        1
      ],
      "f1": 0,
      "precision": 0.0,
      "recall": 0.0,
      "tp": 0,
      "fp": 1,
      "tn": 6,
      "fn": 1
    },
    "hs_based_D_on_src_novc": {
      "interval": [],
      "disfluency_label": [
        0,
        0,
        0,
        0,
        0,
        0,
        0,
        0
      ],
      "f1": 0,
      "precision": 0,
      "recall": 0.0,
      "tp": 0,
      "fp": 0,
      "tn": 7,
      "fn": 1
    },
    "zs_based_D_on_src_novc": {
      "interval": [],
      "disfluency_label": [
        0,
        0,
        0,
        0,
        0,
        0,
        0,
        0
      ],
      "f1": 0,
      "precision": 0,
      "recall": 0.0,
      "tp": 0,
      "fp": 0,
      "tn": 7,
      "fn": 1
    },
    "hs_based_D_on_src": {
      "interval": [],
      "disfluency_label": [
        0,
        0,
        0,
        0,
        0,
        0,
        0,
        0
      ],
      "f1": 0,
      "precision": 0,
      "recall": 0.0,
      "tp": 0,
      "fp": 0,
      "tn": 7,
      "fn": 1
    },
    "zs_based_D_on_src": {
      "interval": [],
      "disfluency_label": [
        0,
        0,
        0,
        0,
        0,
        0,
        0,
        0
      ],
      "f1": 0,
      "precision": 0,
      "recall": 0.0,
      "tp": 0,
      "fp": 0,
      "tn": 7,
      "fn": 1
    },
    "zs_hs_based_D_on_src": {
      "interval": [
        [
          2.69,
          3.01
        ]
      ],
      "disfluency_label": [
        0,
        0,
        0,
        0,
        0,
        0,
        0,
        1
      ],
      "f1": 0,
      "precision": 0.0,
      "recall": 0.0,
      "tp": 0,
      "fp": 1,
      "tn": 6,
      "fn": 1
    },
    "ASR": {
      "disfluency_label": [
        0,
        0,
        0,
        1,
        1,
        0,
        1,
        1
      ],
      "f1": 0,
      "precision": 0.0,
      "recall": 0.0,
      "tp": 0,
      "fp": 4,
      "tn": 3,
      "fn": 1
    }
  }
}